{
    "birth_date": "1958-07-15",
    "source_records": [
        "bwb:9781646979561",
        "promise:bwb_daily_pallets_2022-08-16",
        "promise:bwb_daily_pallets_2022-08-13:O8-ACD-867",
        "amazon:0439408385"
    ],
    "type": {
        "key": "/type/author"
    },
    "alternate_names": [
        "Marcia Thornton"
    ],
    "personal_name": "Marcia Thornton Jones",
    "key": "/authors/OL1385424A",
    "name": "Marcia Thornton Jones",
    "remote_ids": {
        "viaf": "266015170",
        "wikidata": "Q6757113"
    },
    "latest_revision": 9,
    "revision": 9,
    "created": {
        "type": "/type/datetime",
        "value": "2008-04-01T03:28:50.625462"
    },
    "last_modified": {
        "type": "/type/datetime",
        "value": "2023-03-13T20:13:05.630293"
    }
}