{
    "name": "James Logan",
    "key": "/authors/OL15147273A",
    "type": {
        "key": "/type/author"
    },
    "alternate_names": [
        "Logan, James",
        "Logan, J.",
        "J. Logan"
    ],
    "remote_ids": {
        "amazon": "B0C4JHHK12",
        "goodreads": "36640036",
        "lc_naf": "no2024052481",
        "librarything": "loganjames-3"
    },
    "links": [
        {
            "title": "Official Website",
            "url": "https://jamesloganauthor.com",
            "type": {
                "key": "/type/link"
            }
        },
        {
            "title": "Official Blog",
            "url": "https://jamesloganauthor.com/blog",
            "type": {
                "key": "/type/link"
            }
        },
        {
            "title": "Fantastic Fiction Author Entry",
            "url": "https://www.fantasticfiction.com/l/james-logan/",
            "type": {
                "key": "/type/link"
            }
        },
        {
            "title": "ISFDB Author Entry",
            "url": "https://www.isfdb.org/cgi-bin/ea.cgi?377484",
            "type": {
                "key": "/type/link"
            }
        }
    ],
    "photos": [
        14853134,
        14853133,
        14853132
    ],
    "latest_revision": 5,
    "revision": 5,
    "created": {
        "type": "/type/datetime",
        "value": "2025-03-19T01:49:57.206997"
    },
    "last_modified": {
        "type": "/type/datetime",
        "value": "2025-03-19T02:08:56.578943"
    }
}