{
    "type": {
        "key": "/type/author"
    },
    "source_records": [
        "promise:bwb_daily_pallets_2021-06-17"
    ],
    "personal_name": "Gregory Maguire",
    "remote_ids": {
        "viaf": "267230610",
        "wikidata": "Q736137",
        "isni": "0000000401818947"
    },
    "key": "/authors/OL21554A",
    "alternate_names": [
        "maguire-gregory",
        "GREGORY MAGUIRE",
        "Maguire, Gregory",
        "Maguire Gregory"
    ],
    "name": "Gregory Maguire",
    "latest_revision": 6,
    "revision": 6,
    "created": {
        "type": "/type/datetime",
        "value": "2008-04-01T03:28:50.625462"
    },
    "last_modified": {
        "type": "/type/datetime",
        "value": "2024-02-26T07:39:19.397961"
    }
}