{
    "links": [
        {
            "url": "https://en.wikipedia.org/wiki/Steven_Brust",
            "type": {
                "key": "/type/link"
            },
            "title": "Wikipedia entry"
        }
    ],
    "personal_name": "Steven Brust",
    "last_modified": {
        "type": "/type/datetime",
        "value": "2020-09-30T14:22:41.110265"
    },
    "latest_revision": 5,
    "key": "/authors/OL227500A",
    "remote_ids": {
        "viaf": "5074845",
        "wikidata": "Q1780503",
        "isni": "0000000108652300"
    },
    "name": "Steven Brust",
    "created": {
        "type": "/type/datetime",
        "value": "2008-04-01T03:28:50.625462"
    },
    "birth_date": "1955",
    "type": {
        "key": "/type/author"
    },
    "revision": 5
}