{
    "name": "Axel Scheffler",
    "remote_ids": {
        "wikidata": "Q96116",
        "isni": "0000000116806904",
        "viaf": "84723161"
    },
    "source_records": [
        "amazon:1788005414",
        "ia:pipenposyindesne0000sche",
        "amazon:6052953861",
        "bwb:9780857840691",
        "promise:bwb_daily_pallets_2020-09-09",
        "promise:bwb_daily_pallets_2021-02-16",
        "amazon:8423329690",
        "promise:bwb_daily_pallets_2023-08-01:KS-748-099",
        "bwb:9781839942075",
        "bwb:9780702335501"
    ],
    "key": "/authors/OL2493250A",
    "birth_date": "1957-12-12",
    "photos": [
        14586049
    ],
    "type": {
        "key": "/type/author"
    },
    "personal_name": "Axel Scheffler",
    "latest_revision": 11,
    "revision": 11,
    "created": {
        "type": "/type/datetime",
        "value": "2008-04-01T03:28:50.625462"
    },
    "last_modified": {
        "type": "/type/datetime",
        "value": "2024-05-16T08:12:38.154784"
    }
}