{
    "title": "(Choldenko, Gennifer, 1957-)",
    "alternate_names": [
        "Gennifer; trad. de Marie Leymarie Choldenko",
        "Qiu dan ke (Choldenko, Gennifer, 1957-)",
        "Choldenko Gennifer"
    ],
    "name": "Gennifer Choldenko",
    "personal_name": "Gennifer Choldenko",
    "birth_date": "1957",
    "key": "/authors/OL443661A",
    "source_records": [
        "bwb:9781632452511"
    ],
    "type": {
        "key": "/type/author"
    },
    "latest_revision": 3,
    "revision": 3,
    "created": {
        "type": "/type/datetime",
        "value": "2008-04-01T03:28:50.625462"
    },
    "last_modified": {
        "type": "/type/datetime",
        "value": "2025-05-01T01:59:29.762434"
    }
}