{
    "name": "Richard McGuire",
    "personal_name": "Richard McGuire",
    "key": "/authors/OL442637A",
    "type": {
        "key": "/type/author"
    },
    "bio": {
        "type": "/type/text",
        "value": "American illustrator, comic book artist, children's book author, and musician"
    },
    "remote_ids": {
        "wikidata": "Q18694173"
    },
    "birth_date": "1957",
    "photos": [
        14432542
    ],
    "latest_revision": 4,
    "revision": 4,
    "created": {
        "type": "/type/datetime",
        "value": "2008-04-01T03:28:50.625462"
    },
    "last_modified": {
        "type": "/type/datetime",
        "value": "2023-10-06T15:16:50.974602"
    }
}