{
    "name": "Paul Hoffman (English Writer)",
    "personal_name": "Paul Hoffman",
    "key": "/authors/OL6779410A",
    "birth_date": "1953",
    "type": {
        "key": "/type/author"
    },
    "alternate_names": [
        "Paul Hoffman"
    ],
    "bio": {
        "type": "/type/text",
        "value": "Paul Hoffman (born 1953) is an author, who wrote the Left Hand of God trilogy.\r\n\r\nHe studied English at New College, Oxford. Paul Hoffman wrote the script for the 1998 vampire film The Wisdom of Crocodiles with Jude Law, Timothy Spall and Elina L\u00f6wensohn. A portion of his first novel was loosely based on the film of the same name.\r\n\r\nSource: https://en.wikipedia.org/wiki/Paul_Hoffman_(English_writer)"
    },
    "remote_ids": {
        "wikidata": "Q2735982"
    },
    "latest_revision": 2,
    "revision": 2,
    "created": {
        "type": "/type/datetime",
        "value": "2010-01-27T15:37:44.999660"
    },
    "last_modified": {
        "type": "/type/datetime",
        "value": "2021-09-28T21:37:45.827170"
    }
}