{
    "source_records": [
        "bwb:9781801108454"
    ],
    "type": {
        "key": "/type/author"
    },
    "personal_name": "Adrian Tchaikovsky",
    "links": [
        {
            "title": "Official Website",
            "url": "https://www.adriantchaikovsky.com",
            "type": {
                "key": "/type/link"
            }
        },
        {
            "title": "Official Blog",
            "url": "https://www.adriantchaikovsky.com/blog-index.php",
            "type": {
                "key": "/type/link"
            }
        },
        {
            "title": "Blog Archive",
            "url": "https://shadowsoftheapt.com/",
            "type": {
                "key": "/type/link"
            }
        },
        {
            "title": "Fantastic Fiction Author Entry",
            "url": "https://www.fantasticfiction.com/t/adrian-tchaikovsky/",
            "type": {
                "key": "/type/link"
            }
        },
        {
            "title": "ISFDB Author Entry",
            "url": "https://www.isfdb.org/cgi-bin/ea.cgi?111636",
            "type": {
                "key": "/type/link"
            }
        },
        {
            "title": "SFE Author Entry",
            "url": "https://sf-encyclopedia.com/entry/tchaikovsky_adrian",
            "type": {
                "key": "/type/link"
            }
        }
    ],
    "birth_date": "04 June 1972",
    "name": "Adrian Tchaikovsky",
    "key": "/authors/OL7468980A",
    "remote_ids": {
        "storygraph": "e92abad2-5d9d-44a9-babb-b0e1e781fd01",
        "viaf": "102929550",
        "wikidata": "Q4685389",
        "isni": "0000000114964220",
        "bookbrainz": "83b807dc-644b-47e3-821d-63c869fb442c",
        "musicbrainz": "5f2375e8-67d5-410c-9bdb-6793a7c0d62b",
        "imdb": "nm9353166",
        "goodreads": "1445909",
        "librarything": "tchaikovskyadrian",
        "gnd": "139989773",
        "lc_naf": "n2009072685",
        "amazon": "B002XLHS8Q",
        "inventaire": "wd:Q4685389"
    },
    "photos": [
        14852113,
        14852112
    ],
    "latest_revision": 14,
    "revision": 14,
    "created": {
        "type": "/type/datetime",
        "value": "2019-03-06T04:53:32.329596"
    },
    "last_modified": {
        "type": "/type/datetime",
        "value": "2025-03-14T15:39:30.789470"
    }
}